{
  "variables": {
    "virtualbox_source_path": ""
  },
  "builders": [
    {
      "type": "virtualbox-ovf",
      "vm_name": "{{user `author`}}-{{user `name`}}-{{user `version`}}-{{timestamp}}",
      "source_path": "{{user `virtualbox_source_path`}}",
      "headless": "{{user `virtualbox_headless`}}",
      "vboxmanage": [
        [
          "modifyvm",
          "{{.Name}}",
          "--memory",
          "{{user `virtualbox_memory`}}"
        ],
        [
          "modifyvm",
          "{{.Name}}",
          "--cpus",
          "{{user `virtualbox_cpus`}}"
        ]
      ],
      "boot_wait": "{{user `virtualbox_boot_wait`}}",
      "communicator": "{{user `virtualbox_communicator`}}",
      "ssh_username": "{{user `virtualbox_ssh_username`}}",
      "ssh_password": "{{user `virtualbox_ssh_password`}}",
      "ssh_timeout": "{{user `virtualbox_ssh_timeout`}}",
      "guest_additions_mode": "{{user `virtualbox_guest_additions_mode`}}",
      "shutdown_command": "{{user `virtualbox_shutdown_command`}}",
      "shutdown_timeout": "{{user `virtualbox_shutdown_timeout`}}",
      "post_shutdown_delay": "{{user `virtualbox_post_shutdown_delay`}}",
      "output_directory": "{{user `output_directory`}}/build"
    }
  ]
}